[{"AA11":"住","AA12":"","a":"林內鄉新興路","b":"透天厝","bn":"御墅庭IIA","bs":"","bu":"Ca號","cinfo":"","city":"P","commid":"","cp":"","e":"114/04/07","es":"","f":"全/3","fi":"","g":"0","id":"0","j":"1","k":"1","l":"1","lat":23.762483394857068,"lon":120.61635655465668,"m":"","ma":"鋼筋混凝土造","msg":"總價/總面積","note":"車位未單獨計價，且已含入交易總價","p":"","pimg":"bt_02.png","pu":"住家用","punit":"1","r":10,"reid":"G1PA11402070006","s":"46.66","sq":"ilhNxqjmq9+OC5y7RP3skkycldcdixsf7O6OqLYSzUQ=","t":"房地(土地+建物)+車位","town":"P10","tp":"9,600,000","tunit":"1","type":"Sale","unit":"2","v":"5房2廳4衛"},{"AA11":"住","AA12":"","a":"林內鄉新興路","b":"透天厝","bn":"御墅庭IIA","bs":"","bu":"A2號","cinfo":"","city":"P","commid":"","cp":"","e":"114/03/07","es":"","f":"全/3","fi":"","g":"0","id":"1","j":"7","k":"1","l":"1","lat":23.76211395070032,"lon":120.61667158076322,"m":"","ma":"鋼筋混凝土造","msg":"總價/總面積","note":"車位未單獨計價，且已含入交易總價","p":"","pimg":"bt_02.png","pu":"住家用","punit":"1","r":33,"reid":"G1PA11402070006","s":"45.81","sq":"0BtmLet+mW2J+nyCCp5sCkycldcdixsf7O6OqLYSzUQ=","t":"房地(土地+建物)+車位","town":"P10","tp":"8,880,000","tunit":"1","type":"Sale","unit":"2","v":"5房2廳4衛"},{"AA11":"住","AA12":"","a":"林內鄉新興路","b":"透天厝","bn":"御墅庭IIA","bs":"","bu":"A1號","cinfo":"","city":"P","commid":"","cp":"","e":"114/03/03","es":"","f":"全/3","fi":"","g":"0","id":"2","j":"7","k":"1","l":"1","lat":23.762168016380063,"lon":120.61662236877339,"m":"","ma":"鋼筋混凝土造","msg":"總價/總面積","note":"車位未單獨計價，且已含入交易總價","p":"","pimg":"bt_02.png","pu":"住家用","punit":"1","r":33,"reid":"G1PA11402070006","s":"45.81","sq":"0dCNX1Tkp4Gf06EC1Yf9QUycldcdixsf7O6OqLYSzUQ=","t":"房地(土地+建物)+車位","town":"P10","tp":"8,800,000","tunit":"1","type":"Sale","unit":"2","v":"5房2廳4衛"},{"AA11":"住","AA12":"","a":"林內鄉新興路","b":"透天厝","bn":"御墅庭IIA","bs":"","bu":"A3號","cinfo":"","city":"P","commid":"","cp":"","e":"114/03/21","es":"","f":"全/3","fi":"","g":"0","id":"3","j":"7","k":"1","l":"1","lat":23.76218629296674,"lon":120.61671061178066,"m":"","ma":"鋼筋混凝土造","msg":"總價/總面積","note":"車位未單獨計價，且已含入交易總價","p":"","pimg":"bt_02.png","pu":"住家用","punit":"1","r":33,"reid":"G1PA11402070006","s":"46.07","sq":"2Aot6ftU4dEE30siC7QWOEycldcdixsf7O6OqLYSzUQ=","t":"房地(土地+建物)+車位","town":"P10","tp":"9,100,000","tunit":"1","type":"Sale","unit":"2","v":"5房2廳4衛"},{"AA11":"住","AA12":"","a":"林內鄉新興路","b":"透天厝","bn":"御墅庭IIB","bs":"","bu":"B1號","cinfo":"","city":"P","commid":"","cp":"","e":"114/03/24","es":"","f":"全/3","fi":"","g":"0","id":"4","j":"7","k":"1","l":"1","lat":23.762276020475852,"lon":120.61648470210808,"m":"","ma":"鋼筋混凝土造","msg":"總價/總面積","note":"車位未單獨計價，且已含入交易總價","p":"","pimg":"bt_02.png","pu":"住家用","punit":"1","r":33,"reid":"G1PA11402080001","s":"47.84","sq":"1AxUQZXDm4mntW8GSoaFEkycldcdixsf7O6OqLYSzUQ=","t":"房地(土地+建物)+車位","town":"P10","tp":"8,800,000","tunit":"1","type":"Sale","unit":"2","v":"5房2廳4衛"},{"AA11":"住","AA12":"","a":"林內鄉新興路","b":"透天厝","bn":"御墅庭IIA","bs":"","bu":"A6號","cinfo":"","city":"P","commid":"","cp":"","e":"114/03/15","es":"","f":"全/3","fi":"","g":"0","id":"5","j":"7","k":"1","l":"1","lat":23.762285901255666,"lon":120.61682804887359,"m":"","ma":"鋼筋混凝土造","msg":"總價/總面積","note":"車位未單獨計價，且已含入交易總價","p":"","pimg":"bt_02.png","pu":"住家用","punit":"1","r":33,"reid":"G1PA11402070006","s":"47.84","sq":"DUp9d44YV7ctPFzMl5IN1Uycldcdixsf7O6OqLYSzUQ=","t":"房地(土地+建物)+車位","town":"P10","tp":"8,500,000","tunit":"1","type":"Sale","unit":"2","v":"4房3廳4衛"},{"AA11":"住","AA12":"","a":"林內鄉新興路","b":"透天厝","bn":"御墅庭IIB","bs":"","bu":"B3號","cinfo":"","city":"P","commid":"","cp":"","e":"114/03/21","es":"","f":"全/3","fi":"","g":"0","id":"6","j":"7","k":"1","l":"1","lat":23.76233945579209,"lon":120.61657281286165,"m":"","ma":"鋼筋混凝土造","msg":"總價/總面積","note":"車位未單獨計價，且已含入交易總價","p":"","pimg":"bt_02.png","pu":"住家用","punit":"1","r":33,"reid":"G1PA11402080001","s":"46.07","sq":"RogemXSEgqNUZMXwpYTnHEycldcdixsf7O6OqLYSzUQ=","t":"房地(土地+建物)+車位","town":"P10","tp":"9,100,000","tunit":"1","type":"Sale","unit":"2","v":"5房2廳4衛"},{"AA11":"住","AA12":"","a":"林內鄉新興路","b":"透天厝","bn":"御墅庭IIA","bs":"","bu":"C1號","cinfo":"","city":"P","commid":"","cp":"","e":"114/03/01","es":"","f":"全/3","fi":"","g":"0","id":"7","j":"1","k":"1","l":"1","lat":23.762393384768906,"lon":120.61647454743164,"m":"","ma":"鋼筋混凝土造","msg":"總價/總面積","note":"車位未單獨計價，且已含入交易總價","p":"","pimg":"bt_02.png","pu":"住家用","punit":"1","r":11,"reid":"G1PA11402070006","s":"46.66","sq":"AkKc3chcv2BItEGHFgc1EUycldcdixsf7O6OqLYSzUQ=","t":"房地(土地+建物)+車位","town":"P10","tp":"10,200,000","tunit":"1","type":"Sale","unit":"2","v":"4房2廳4衛"},{"AA11":"住","AA12":"","a":"林內鄉新興路","b":"透天厝","bn":"御墅庭IIB","bs":"","bu":"B5號","cinfo":"","city":"P","commid":"","cp":"","e":"114/03/26","es":"","f":"全/3","fi":"","g":"0","id":"8","j":"7","k":"1","l":"1","lat":23.762420860624847,"lon":120.61663143883054,"m":"","ma":"鋼筋混凝土造","msg":"總價/總面積","note":"車位未單獨計價，且已含入交易總價","p":"","pimg":"bt_02.png","pu":"住家用","punit":"1","r":33,"reid":"G1PA11402080001","s":"46.07","sq":"Lb0hN6j3GmT9J85JMn457Uycldcdixsf7O6OqLYSzUQ=","t":"房地(土地+建物)+車位","town":"P10","tp":"9,500,000","tunit":"1","type":"Sale","unit":"2","v":"5房2廳4衛"},{"AA11":"住","AA12":"","a":"林內鄉新興路","b":"透天厝","bn":"御墅庭IIB","bs":"","bu":"C2號","cinfo":"","city":"P","commid":"","cp":"","e":"114/03/08","es":"","f":"全/3","fi":"","g":"0","id":"9","j":"1","k":"1","l":"1","lat":23.76242942669901,"lon":120.61644500957189,"m":"","ma":"鋼筋混凝土造","msg":"總價/總面積","note":"車位未單獨計價，且已含入交易總價","p":"","pimg":"bt_02.png","pu":"住家用","punit":"1","r":11,"reid":"G1PA11402080001","s":"46.66","sq":"BmBy+743s/mAPnTlqiwMskycldcdixsf7O6OqLYSzUQ=","t":"房地(土地+建物)+車位","town":"P10","tp":"9,600,000","tunit":"1","type":"Sale","unit":"2","v":"5房2廳4衛"},{"AA11":"住","AA12":"","a":"林內鄉新興路","b":"透天厝","bn":"御墅庭IIB","bs":"","bu":"B6號","cinfo":"","city":"P","commid":"","cp":"","e":"114/03/28","es":"","f":"全/3","fi":"","g":"0","id":"10","j":"7","k":"1","l":"1","lat":23.762439064186214,"lon":120.61669024998376,"m":"","ma":"鋼筋混凝土造","msg":"總價/總面積","note":"車位未單獨計價，且已含入交易總價","p":"","pimg":"bt_02.png","pu":"住家用","punit":"1","r":33,"reid":"G1PA11402080001","s":"43.30","sq":"B+hZ/qFyFLHmK2opMsbhZUycldcdixsf7O6OqLYSzUQ=","t":"房地(土地+建物)+車位","town":"P10","tp":"8,380,000","tunit":"1","type":"Sale","unit":"2","v":"5房2廳4衛"},{"AA11":"住","AA12":"","a":"林內鄉新興路","b":"透天厝","bn":"御墅庭IIB","bs":"","bu":"C3號","cinfo":"","city":"P","commid":"","cp":"","e":"114/03/08","es":"","f":"全/3","fi":"","g":"0","id":"11","j":"1","k":"1","l":"1","lat":23.762447362404238,"lon":120.61639590327198,"m":"","ma":"鋼筋混凝土造","msg":"總價/總面積","note":"車位未單獨計價，且已含入交易總價","p":"","pimg":"bt_02.png","pu":"住家用","punit":"1","r":10,"reid":"G1PA11402080001","s":"46.66","sq":"QYDJuLmXc69ERJTr82sVOkycldcdixsf7O6OqLYSzUQ=","t":"房地(土地+建物)+車位","town":"P10","tp":"10,000,000","tunit":"1","type":"Sale","unit":"2","v":"5房2廳4衛"},{"AA11":"特定農業區","AA12":"甲種建築用地","a":"林內鄉仁愛路","b":"透天厝","bn":"愛上林內","bs":"","bu":"C2號","cinfo":"","city":"P","commid":"","cp":"","e":"113/12/07","es":"","f":"全/3","fi":"","g":"0","id":"12","j":"3","k":"1","l":"0","lat":23.76638608902154,"lon":120.61348028881068,"m":"","ma":"鋼筋混凝土造","msg":"總價/總面積","note":"","p":"","pimg":"bt_02.png","pu":"住家用","punit":"1","r":17,"reid":"G1PA11301050002","s":"41.00","sq":"kff+6WQS5Hg98mFBjN5/FUycldcdixsf7O6OqLYSzUQ=","t":"房地(土地+建物)","town":"P10","tp":"9,450,000","tunit":"1","type":"Sale","unit":"2","v":"4房2廳3衛"},{"AA11":"住","AA12":"","a":"林內鄉新興路","b":"透天厝","bn":"墅合院三","bs":"","bu":"G5棟0號","cinfo":"","city":"P","commid":"","cp":"","e":"113/07/09","es":"","f":"全/4","fi":"","g":"0","id":"13","j":"3","k":"1","l":"0","lat":23.762835180374946,"lon":120.61620836175868,"m":"","ma":"鋼筋混凝土造","msg":"總價/總面積","note":"","p":"","pimg":"bt_02.png","pu":"住家用","punit":"1","r":16,"reid":"","s":"50.21","sq":"cfDgzFMN3hHB1Ldjrz6l6kycldcdixsf7O6OqLYSzUQ=","t":"房地(土地+建物)","town":"P10","tp":"8,900,000","tunit":"1","type":"Sale","unit":"2","v":"4房2廳5衛"},{"AA11":"特定農業區","AA12":"甲種建築用地","a":"林內鄉仁愛路","b":"透天厝","bn":"愛上林內","bs":"","bu":"B1號","cinfo":"","city":"P","commid":"","cp":"","e":"113/07/27","es":"","f":"全/3","fi":"","g":"0","id":"14","j":"3","k":"1","l":"0","lat":23.766169442945994,"lon":120.6135103618508,"m":"","ma":"鋼筋混凝土造","msg":"總價/總面積","note":"","p":"","pimg":"bt_02.png","pu":"住家用","punit":"1","r":17,"reid":"G1PA11301050002","s":"40.02","sq":"oNg7/n//tF6SnF13Yhdyv0ycldcdixsf7O6OqLYSzUQ=","t":"房地(土地+建物)","town":"P10","tp":"9,450,000","tunit":"1","type":"Sale","unit":"2","v":"4房2廳3衛"},{"AA11":"特定農業區","AA12":"甲種建築用地","a":"林內鄉仁愛路","b":"透天厝","bn":"愛上林內","bs":"","bu":"B3號","cinfo":"","city":"P","commid":"","cp":"","e":"113/07/13","es":"","f":"全/3","fi":"","g":"0","id":"15","j":"3","k":"1","l":"0","lat":23.766232879974037,"lon":120.6135984737293,"m":"","ma":"鋼筋混凝土造","msg":"總價/總面積","note":"","p":"","pimg":"bt_02.png","pu":"住家用","punit":"1","r":16,"reid":"G1PA11301050002","s":"40.02","sq":"2v6neNkrvURNBuydfl9b+Eycldcdixsf7O6OqLYSzUQ=","t":"房地(土地+建物)","town":"P10","tp":"9,150,000","tunit":"1","type":"Sale","unit":"2","v":"4房2廳3衛"},{"AA11":"住","AA12":"","a":"林內鄉新興路","b":"透天厝","bn":"墅合院三","bs":"","bu":"G6棟0號","cinfo":"","city":"P","commid":"","cp":"","e":"113/06/23","es":"","f":"全/4","fi":"","g":"0","id":"16","j":"3","k":"1","l":"0","lat":23.76286238847928,"lon":120.61625733585537,"m":"","ma":"鋼筋混凝土造","msg":"總價/總面積","note":"","p":"","pimg":"bt_02.png","pu":"住家用","punit":"1","r":16,"reid":"","s":"50.21","sq":"h+NDpoGswh+drPYkz9j6A0ycldcdixsf7O6OqLYSzUQ=","t":"房地(土地+建物)","town":"P10","tp":"9,200,000","tunit":"1","type":"Sale","unit":"2","v":"4房2廳5衛"},{"AA11":"特定農業區","AA12":"甲種建築用地","a":"林內鄉仁愛路","b":"透天厝","bn":"愛上林內","bs":"","bu":"B2號","cinfo":"","city":"P","commid":"","cp":"","e":"113/04/11","es":"","f":"全/3","fi":"","g":"0","id":"17","j":"1","k":"1","l":"0","lat":23.766241540524618,"lon":120.61345128271878,"m":"","ma":"鋼筋混凝土造","msg":"總價/總面積","note":"","p":"","pimg":"bt_02.png","pu":"住家用","punit":"1","r":34,"reid":"G1PA11301050002","s":"37.81","sq":"bR9HBsWgqvwuPEdvsbQQiUycldcdixsf7O6OqLYSzUQ=","t":"房地(土地+建物)","town":"P10","tp":"9,150,000","tunit":"1","type":"Sale","unit":"2","v":"4房2廳3衛"},{"AA11":"特定農業區","AA12":"甲種建築用地","a":"林內鄉仁愛路","b":"透天厝","bn":"愛上林內","bs":"","bu":"A6號","cinfo":"","city":"P","commid":"","cp":"","e":"113/04/20","es":"","f":"全/3","fi":"","g":"0","id":"18","j":"1","k":"1","l":"0","lat":23.766241540524618,"lon":120.61345128271878,"m":"","ma":"鋼筋混凝土造","msg":"總價/總面積","note":"","p":"","pimg":"bt_02.png","pu":"住家用","punit":"1","r":34,"reid":"G1PA11301050002","s":"36.91","sq":"FY6TGvfJEhiQlqb00v/sSUycldcdixsf7O6OqLYSzUQ=","t":"房地(土地+建物)","town":"P10","tp":"9,600,000","tunit":"1","type":"Sale","unit":"2","v":"4房2廳3衛"},{"AA11":"特定農業區","AA12":"甲種建築用地","a":"林內鄉仁愛路","b":"透天厝","bn":"愛上林內","bs":"","bu":"A3號","cinfo":"","city":"P","commid":"","cp":"","e":"113/04/27","es":"","f":"全/3","fi":"","g":"0","id":"19","j":"1","k":"1","l":"0","lat":23.76624107394157,"lon":120.61326487454902,"m":"","ma":"鋼筋混凝土造","msg":"總價/總面積","note":"","p":"","pimg":"bt_02.png","pu":"住家用","punit":"1","r":5,"reid":"G1PA11301050002","s":"36.91","sq":"o04AIR7w/82j1BHm/DwXdUycldcdixsf7O6OqLYSzUQ=","t":"房地(土地+建物)","town":"P10","tp":"9,580,000","tunit":"1","type":"Sale","unit":"2","v":"4房2廳3衛"},{"AA11":"住","AA12":"","a":"林內鄉新興路","b":"透天厝","bn":"御墅庭A","bs":"","bu":"B3號","cinfo":"","city":"P","commid":"","cp":"","e":"113/03/26","es":"","f":"全/3","fi":"","g":"0","id":"20","j":"6","k":"1","l":"1","lat":23.76197933183214,"lon":120.6170055392724,"m":"","ma":"鋼筋混凝土造","msg":"總價/總面積","note":"","p":"","pimg":"bt_02.png","pu":"住家用","punit":"1","r":32,"reid":"G1PA11301170001","s":"42.42","sq":"4HT1gHWvbXbMWCDKdKqTmkycldcdixsf7O6OqLYSzUQ=","t":"房地(土地+建物)+車位","town":"P10","tp":"7,800,000","tunit":"1","type":"Sale","unit":"2","v":"5房2廳5衛"},{"AA11":"住","AA12":"","a":"林內鄉新興路","b":"透天厝","bn":"御墅庭B","bs":"","bu":"B6號","cinfo":"","city":"P","commid":"","cp":"","e":"113/03/22","es":"","f":"全/3","fi":"","g":"0","id":"21","j":"6","k":"1","l":"1","lat":23.76206909901591,"lon":120.61678944075875,"m":"","ma":"鋼筋混凝土造","msg":"總價/總面積","note":"","p":"","pimg":"bt_02.png","pu":"住家用","punit":"1","r":32,"reid":"G1PA11301170002","s":"48.98","sq":"UqHjhWs8sWmh1EBgSY6iDkycldcdixsf7O6OqLYSzUQ=","t":"房地(土地+建物)+車位","town":"P10","tp":"8,400,000","tunit":"1","type":"Sale","unit":"2","v":"4房3廳4衛"},{"AA11":"住","AA12":"","a":"林內鄉新興路","b":"透天厝","bn":"御墅庭B","bs":"","bu":"A3號","cinfo":"","city":"P","commid":"","cp":"","e":"113/02/25","es":"","f":"全/3","fi":"","g":"0","id":"22","j":"6","k":"1","l":"1","lat":23.761996781106454,"lon":120.61676022037342,"m":"","ma":"鋼筋混凝土造","msg":"總價/總面積","note":"","p":"","pimg":"bt_02.png","pu":"住家用","punit":"1","r":32,"reid":"","s":"45.46","sq":"CSbgTG973OJpo1enX3XQ2Eycldcdixsf7O6OqLYSzUQ=","t":"房地(土地+建物)+車位","town":"P10","tp":"8,800,000","tunit":"1","type":"Sale","unit":"2","v":"4房3廳4衛"},{"AA11":"住","AA12":"","a":"林內鄉新興路","b":"透天厝","bn":"御墅庭B","bs":"","bu":"Aa號","cinfo":"","city":"P","commid":"","cp":"","e":"113/02/25","es":"","f":"全/3","fi":"","g":"0","id":"23","j":"5","k":"1","l":"1","lat":23.762050846815463,"lon":120.61671100846455,"m":"","ma":"鋼筋混凝土造","msg":"總價/總面積","note":"","p":"","pimg":"bt_02.png","pu":"住家用","punit":"1","r":28,"reid":"","s":"45.46","sq":"qt06X0OrfNQqM7pDbdM79Eycldcdixsf7O6OqLYSzUQ=","t":"房地(土地+建物)+車位","town":"P10","tp":"8,800,000","tunit":"1","type":"Sale","unit":"2","v":"4房3廳4衛"},{"AA11":"住","AA12":"","a":"林內鄉新興路","b":"透天厝","bn":"御墅庭A","bs":"","bu":"B1號","cinfo":"","city":"P","commid":"","cp":"","e":"113/02/23","es":"","f":"全/3","fi":"","g":"0","id":"24","j":"6","k":"1","l":"1","lat":23.761915960316273,"lon":120.61693704977385,"m":"","ma":"鋼筋混凝土造","msg":"總價/總面積","note":"","p":"","pimg":"bt_02.png","pu":"住家用","punit":"1","r":32,"reid":"","s":"48.98","sq":"Wa+YmfGiXkdS+XdwJAuV3Eycldcdixsf7O6OqLYSzUQ=","t":"房地(土地+建物)+車位","town":"P10","tp":"8,100,000","tunit":"1","type":"Sale","unit":"2","v":"4房4廳4衛"},{"AA11":"住","AA12":"","a":"林內鄉新興路","b":"透天厝","bn":"御墅庭A","bs":"","bu":"B2號","cinfo":"","city":"P","commid":"","cp":"","e":"113/02/26","es":"","f":"全/3","fi":"","g":"0","id":"25","j":"6","k":"1","l":"1","lat":23.76194314386436,"lon":120.6169762130462,"m":"","ma":"鋼筋混凝土造","msg":"總價/總面積","note":"","p":"","pimg":"bt_02.png","pu":"住家用","punit":"1","r":32,"reid":"","s":"48.98","sq":"p2BEH0WCwfua/TMaemYj9kycldcdixsf7O6OqLYSzUQ=","t":"房地(土地+建物)+車位","town":"P10","tp":"8,100,000","tunit":"1","type":"Sale","unit":"2","v":"5房3廳4衛"},{"AA11":"住","AA12":"","a":"林內鄉新興路","b":"透天厝","bn":"御墅庭B","bs":"","bu":"B9號","cinfo":"","city":"P","commid":"","cp":"","e":"113/02/03","es":"","f":"全/3","fi":"","g":"0","id":"26","j":"6","k":"1","l":"1","lat":23.762150649743855,"lon":120.61690693066717,"m":"","ma":"鋼筋混凝土造","msg":"總價/總面積","note":"","p":"","pimg":"bt_02.png","pu":"住家用","punit":"1","r":32,"reid":"","s":"42.42","sq":"HgO1wTWml4pnnkSB3jFte0ycldcdixsf7O6OqLYSzUQ=","t":"房地(土地+建物)+車位","town":"P10","tp":"7,600,000","tunit":"1","type":"Sale","unit":"2","v":"3房3廳4衛"},{"AA11":"住","AA12":"","a":"林內鄉新興路","b":"透天厝","bn":"御墅庭B","bs":"","bu":"B8號","cinfo":"","city":"P","commid":"","cp":"","e":"113/01/29","es":"","f":"全/3","fi":"","g":"0","id":"27","j":"6","k":"1","l":"1","lat":23.7621234661776,"lon":120.61686776734804,"m":"","ma":"鋼筋混凝土造","msg":"總價/總面積","note":"","p":"","pimg":"bt_02.png","pu":"住家用","punit":"1","r":32,"reid":"","s":"42.42","sq":"HZq8ORJykphBwUe46GiuP0ycldcdixsf7O6OqLYSzUQ=","t":"房地(土地+建物)+車位","town":"P10","tp":"7,600,000","tunit":"1","type":"Sale","unit":"2","v":"4房2廳4衛"},{"AA11":"住","AA12":"","a":"林內鄉新興路","b":"透天厝","bn":"御墅庭A","bs":"","bu":"Ba號","cinfo":"","city":"P","commid":"","cp":"","e":"113/01/26","es":"","f":"全/3","fi":"","g":"0","id":"28","j":"6","k":"1","l":"1","lat":23.76199748661291,"lon":120.61704472899753,"m":"","ma":"鋼筋混凝土造","msg":"總價/總面積","note":"","p":"","pimg":"bt_02.png","pu":"住家用","punit":"1","r":32,"reid":"","s":"42.42","sq":"81F565rDLHvhc1hMXZOVU0ycldcdixsf7O6OqLYSzUQ=","t":"房地(土地+建物)+車位","town":"P10","tp":"7,500,000","tunit":"1","type":"Sale","unit":"2","v":"5房2廳4衛"},{"AA11":"住","AA12":"","a":"林內鄉新興路","b":"透天厝","bn":"御墅庭B","bs":"","bu":"B7號","cinfo":"","city":"P","commid":"","cp":"","e":"113/01/26","es":"","f":"全/3","fi":"","g":"0","id":"29","j":"6","k":"1","l":"1","lat":23.762096282601604,"lon":120.61682860404522,"m":"","ma":"鋼筋混凝土造","msg":"總價/總面積","note":"","p":"","pimg":"bt_02.png","pu":"住家用","punit":"1","r":32,"reid":"","s":"48.98","sq":"e2KTHFb0mnZ00Suzv/dr+Eycldcdixsf7O6OqLYSzUQ=","t":"房地(土地+建物)+車位","town":"P10","tp":"8,450,000","tunit":"1","type":"Sale","unit":"2","v":"4房2廳5衛"},{"AA11":"住","AA12":"","a":"林內鄉新興路","b":"透天厝","bn":"御墅庭A","bs":"","bu":"A1號","cinfo":"","city":"P","commid":"","cp":"","e":"113/01/29","es":"","f":"全/3","fi":"","g":"0","id":"30","j":"5","k":"1","l":"1","lat":23.7618436181065,"lon":120.61689801870871,"m":"","ma":"鋼筋混凝土造","msg":"總價/總面積","note":"","p":"","pimg":"bt_02.png","pu":"住家用","punit":"1","r":28,"reid":"","s":"48.38","sq":"vvo9LHp5f931j7zxuMGhdUycldcdixsf7O6OqLYSzUQ=","t":"房地(土地+建物)+車位","town":"P10","tp":"8,670,000","tunit":"1","type":"Sale","unit":"2","v":"4房2廳5衛"},{"AA11":"住","AA12":"","a":"林內鄉新興路","b":"透天厝","bn":"御墅庭A","bs":"","bu":"A2號","cinfo":"","city":"P","commid":"","cp":"","e":"113/01/29","es":"","f":"全/3","fi":"","g":"0","id":"31","j":"6","k":"1","l":"1","lat":23.76189768386087,"lon":120.61684880691467,"m":"","ma":"鋼筋混凝土造","msg":"總價/總面積","note":"","p":"","pimg":"bt_02.png","pu":"住家用","punit":"1","r":32,"reid":"","s":"45.46","sq":"actSttdfO+xVzHUmUOBcbkycldcdixsf7O6OqLYSzUQ=","t":"房地(土地+建物)+車位","town":"P10","tp":"8,670,000","tunit":"1","type":"Sale","unit":"2","v":"4房2廳5衛"},{"AA11":"住","AA12":"","a":"林內鄉新興路","b":"透天厝","bn":"墅合院三","bs":"","bu":"G9棟0號","cinfo":"","city":"P","commid":"","cp":"","e":"112/07/22","es":"","f":"全/4","fi":"","g":"0","id":"32","j":"3","k":"1","l":"0","lat":23.762681822956527,"lon":120.61626767608725,"m":"","ma":"鋼筋混凝土造","msg":"總價/總面積","note":"","p":"","pimg":"bt_02.png","pu":"住家用","punit":"1","r":16,"reid":"","s":"53.84","sq":"V+HxtTxyL3qrLVZaTS7tdEycldcdixsf7O6OqLYSzUQ=","t":"房地(土地+建物)","town":"P10","tp":"8,480,000","tunit":"1","type":"Sale","unit":"2","v":"4房2廳5衛"},{"AA11":"鄉村區","AA12":"乙種建築用地","a":"林內鄉民權路","b":"透天厝","bn":"姮興光禾墅","bs":"","bu":"A7棟0號","cinfo":"","city":"P","commid":"","cp":"","e":"112/06/12","es":"","f":"全/3","fi":"","g":"0","id":"33","j":"1","k":"1","l":"0","lat":23.747513073874057,"lon":120.60245113908657,"m":"","ma":"鋼筋混凝土造","msg":"總價/總面積","note":"","p":"","pimg":"bt_02.png","pu":"住家用","punit":"1","r":9,"reid":"","s":"44.02","sq":"F73kD1JyHkYGHTvFw3LIG0ycldcdixsf7O6OqLYSzUQ=","t":"房地(土地+建物)","town":"P10","tp":"6,600,000","tunit":"1","type":"Sale","unit":"2","v":"3房2廳3衛"},{"AA11":"住","AA12":"","a":"林內鄉新興路","b":"透天厝","bn":"墅合院三","bs":"","bu":"G3棟0號","cinfo":"","city":"P","commid":"","cp":"","e":"112/06/30","es":"","f":"全/4","fi":"","g":"0","id":"34","j":"3","k":"1","l":"0","lat":23.762798967881356,"lon":120.61616922486554,"m":"","ma":"鋼筋混凝土造","msg":"總價/總面積","note":"","p":"","pimg":"bt_02.png","pu":"住家用","punit":"1","r":16,"reid":"","s":"53.54","sq":"8zJoYz2ZN7GKxgJb4GNWD0ycldcdixsf7O6OqLYSzUQ=","t":"房地(土地+建物)","town":"P10","tp":"8,500,000","tunit":"1","type":"Sale","unit":"2","v":"4房2廳5衛"},{"AA11":"鄉村區","AA12":"乙種建築用地","a":"林內鄉民權路","b":"透天厝","bn":"姮興光禾墅","bs":"","bu":"A5棟0號","cinfo":"","city":"P","commid":"","cp":"","e":"112/05/20","es":"","f":"全/3","fi":"","g":"0","id":"35","j":"1","k":"1","l":"0","lat":23.747549012179913,"lon":120.60238236265843,"m":"","ma":"鋼筋混凝土造","msg":"總價/總面積","note":"","p":"","pimg":"bt_02.png","pu":"住家用","punit":"1","r":9,"reid":"","s":"44.02","sq":"lKUSg/WpToT9LBRnorM16Uycldcdixsf7O6OqLYSzUQ=","t":"房地(土地+建物)","town":"P10","tp":"6,600,000","tunit":"1","type":"Sale","unit":"2","v":"3房2廳3衛"},{"AA11":"鄉村區","AA12":"乙種建築用地","a":"林內鄉民權路","b":"透天厝","bn":"姮興光禾墅","bs":"","bu":"A6棟0號","cinfo":"","city":"P","commid":"","cp":"","e":"112/02/25","es":"","f":"全/3","fi":"","g":"0","id":"36","j":"1","k":"1","l":"0","lat":23.74753105564742,"lon":120.6024216556478,"m":"","ma":"鋼筋混凝土造","msg":"總價/總面積","note":"","p":"","pimg":"bt_02.png","pu":"住家用","punit":"1","r":9,"reid":"","s":"43.99","sq":"wkvKHO5gxi1YB27cDI5R5Uycldcdixsf7O6OqLYSzUQ=","t":"房地(土地+建物)","town":"P10","tp":"6,600,000","tunit":"1","type":"Sale","unit":"2","v":"3房2廳3衛"},{"AA11":"鄉村區","AA12":"乙種建築用地","a":"林內鄉民權路","b":"透天厝","bn":"姮興光禾墅","bs":"","bu":"A3棟0號","cinfo":"","city":"P","commid":"","cp":"","e":"111/12/26","es":"","f":"全/3","fi":"","g":"0","id":"37","j":"1","k":"1","l":"0","lat":23.74756698360308,"lon":120.60234306961314,"m":"","ma":"鋼筋混凝土造","msg":"總價/總面積","note":"","p":"","pimg":"bt_02.png","pu":"住家用","punit":"1","r":9,"reid":"","s":"43.99","sq":"l5JLkWqTNy8aR0pr9cwQQUycldcdixsf7O6OqLYSzUQ=","t":"房地(土地+建物)","town":"P10","tp":"6,600,000","tunit":"1","type":"Sale","unit":"2","v":"3房2廳3衛"},{"AA11":"住","AA12":"","a":"林內鄉新興路","b":"透天厝","bn":"墅合院三","bs":"","bu":"G10棟0號","cinfo":"","city":"P","commid":"","cp":"","e":"111/10/17","es":"","f":"全/4","fi":"","g":"0","id":"38","j":"3","k":"1","l":"0","lat":23.76272708854069,"lon":120.61631659719839,"m":"","ma":"鋼筋混凝土造","msg":"總價/總面積","note":"","p":"","pimg":"bt_02.png","pu":"住家用","punit":"1","r":17,"reid":"","s":"52.03","sq":"bGORPqA/MdhArFxDOqYAckycldcdixsf7O6OqLYSzUQ=","t":"房地(土地+建物)","town":"P10","tp":"8,800,000","tunit":"1","type":"Sale","unit":"2","v":"4房2廳5衛"},{"AA11":"住","AA12":"","a":"林內鄉新興路","b":"透天厝","bn":"墅合院三","bs":"","bu":"G2棟0號","cinfo":"","city":"P","commid":"","cp":"","e":"111/09/01","es":"","f":"全/4","fi":"","g":"0","id":"39","j":"3","k":"1","l":"0","lat":23.76277178412755,"lon":120.61613006151049,"m":"","ma":"鋼筋混凝土造","msg":"總價/總面積","note":"","p":"","pimg":"bt_02.png","pu":"住家用","punit":"1","r":16,"reid":"","s":"55.05","sq":"LTcG0lxVmADgG/zH8jk7OEycldcdixsf7O6OqLYSzUQ=","t":"房地(土地+建物)","town":"P10","tp":"8,600,000","tunit":"1","type":"Sale","unit":"2","v":"4房2廳5衛"},{"AA11":"鄉村區","AA12":"乙種建築用地","a":"林內鄉民權路","b":"透天厝","bn":"姮興光禾墅","bs":"","bu":"A8棟0號","cinfo":"","city":"P","commid":"","cp":"","e":"111/09/06","es":"","f":"全/3","fi":"","g":"0","id":"40","j":"1","k":"1","l":"0","lat":23.7474951173238,"lon":120.60249043205596,"m":"","ma":"鋼筋混凝土造","msg":"總價/總面積","note":"","p":"","pimg":"bt_02.png","pu":"住家用","punit":"1","r":9,"reid":"","s":"43.99","sq":"9098zn6J+v4Sqov67+ubQEycldcdixsf7O6OqLYSzUQ=","t":"房地(土地+建物)","town":"P10","tp":"6,500,000","tunit":"1","type":"Sale","unit":"2","v":"3房2廳3衛"},{"AA11":"住","AA12":"","a":"林內鄉新興路","b":"透天厝","bn":"墅合院三","bs":"","bu":"G7棟0號","cinfo":"","city":"P","commid":"","cp":"","e":"111/09/30","es":"","f":"全/4","fi":"","g":"0","id":"41","j":"3","k":"1","l":"0","lat":23.76262741621465,"lon":120.61617953877631,"m":"","ma":"鋼筋混凝土造","msg":"總價/總面積","note":"","p":"","pimg":"bt_02.png","pu":"住家用","punit":"1","r":17,"reid":"","s":"55.05","sq":"3Z2NXaKKRlUtVAx9h01hp0ycldcdixsf7O6OqLYSzUQ=","t":"房地(土地+建物)","town":"P10","tp":"8,800,000","tunit":"1","type":"Sale","unit":"2","v":"4房2廳5衛"},{"AA11":"住","AA12":"","a":"林內鄉新興路","b":"透天厝","bn":"墅合院三","bs":"","bu":"G8棟0號","cinfo":"","city":"P","commid":"","cp":"","e":"111/09/30","es":"","f":"全/4","fi":"","g":"0","id":"42","j":"3","k":"1","l":"0","lat":23.762654639227865,"lon":120.61622851274608,"m":"","ma":"鋼筋混凝土造","msg":"總價/總面積","note":"","p":"","pimg":"bt_02.png","pu":"住家用","punit":"1","r":16,"reid":"","s":"55.05","sq":"O4V7DBdu3/sWokt9OcH3tkycldcdixsf7O6OqLYSzUQ=","t":"房地(土地+建物)","town":"P10","tp":"8,400,000","tunit":"1","type":"Sale","unit":"2","v":"4房2廳5衛"},{"AA11":"住","AA12":"","a":"林內鄉新興路","b":"透天厝","bn":"墅合院三","bs":"","bu":"G1棟0號","cinfo":"","city":"P","commid":"","cp":"","e":"111/08/21","es":"","f":"全/4","fi":"","g":"0","id":"43","j":"3","k":"1","l":"0","lat":23.762726503584084,"lon":120.61608114049203,"m":"","ma":"鋼筋混凝土造","msg":"總價/總面積","note":"","p":"","pimg":"bt_02.png","pu":"住家用","punit":"1","r":17,"reid":"","s":"56.87","sq":"tewN3XKMGOtnnexSN2Kc5Eycldcdixsf7O6OqLYSzUQ=","t":"房地(土地+建物)","town":"P10","tp":"8,900,000","tunit":"1","type":"Sale","unit":"2","v":"4房2廳5衛"},{"AA11":"鄉村區","AA12":"乙種建築用地","a":"林內鄉民權路","b":"透天厝","bn":"姮興光禾墅","bs":"","bu":"B5棟0號","cinfo":"","city":"P","commid":"","cp":"","e":"111/08/09","es":"","f":"全/3","fi":"","g":"0","id":"44","j":"2","k":"1","l":"0","lat":23.747458447207386,"lon":120.60227473188694,"m":"","ma":"鋼筋混凝土造","msg":"總價/總面積","note":"","p":"","pimg":"bt_02.png","pu":"住家用","punit":"1","r":20,"reid":"","s":"43.97","sq":"J21fJok2rmfbQl4pEgcLDEycldcdixsf7O6OqLYSzUQ=","t":"房地(土地+建物)","town":"P10","tp":"6,550,000","tunit":"1","type":"Sale","unit":"2","v":"3房2廳3衛"},{"AA11":"鄉村區","AA12":"乙種建築用地","a":"林內鄉民權路","b":"透天厝","bn":"姮興光禾墅","bs":"","bu":"B3棟0號","cinfo":"","city":"P","commid":"","cp":"","e":"111/07/30","es":"","f":"全/3","fi":"","g":"0","id":"45","j":"2","k":"1","l":"0","lat":23.747476403702557,"lon":120.60223543889994,"m":"","ma":"鋼筋混凝土造","msg":"總價/總面積","note":"","p":"","pimg":"bt_02.png","pu":"住家用","punit":"1","r":20,"reid":"","s":"44.00","sq":"KfM2At4ra9nVM3dURYR1gEycldcdixsf7O6OqLYSzUQ=","t":"房地(土地+建物)","town":"P10","tp":"6,550,000","tunit":"1","type":"Sale","unit":"2","v":"3房2廳3衛"},{"AA11":"鄉村區","AA12":"乙種建築用地","a":"林內鄉民權路","b":"透天厝","bn":"姮興光禾墅","bs":"","bu":"D3棟0號","cinfo":"","city":"P","commid":"","cp":"","e":"111/07/03","es":"","f":"全/3","fi":"","g":"0","id":"46","j":"2","k":"1","l":"0","lat":23.7473496582877,"lon":120.60210829899934,"m":"","ma":"鋼筋混凝土造","msg":"總價/總面積","note":"","p":"","pimg":"bt_02.png","pu":"住家用","punit":"1","r":20,"reid":"","s":"43.27","sq":"lJ4xVSxr7EPglB6lMnKUPkycldcdixsf7O6OqLYSzUQ=","t":"房地(土地+建物)","town":"P10","tp":"6,300,000","tunit":"1","type":"Sale","unit":"2","v":"3房2廳3衛"},{"AA11":"鄉村區","AA12":"乙種建築用地","a":"林內鄉民權路","b":"透天厝","bn":"姮興光禾墅","bs":"","bu":"D5棟0號","cinfo":"","city":"P","commid":"","cp":"","e":"111/06/11","es":"","f":"全/3","fi":"","g":"0","id":"47","j":"2","k":"1","l":"0","lat":23.74733170182458,"lon":120.60214759196496,"m":"","ma":"鋼筋混凝土造","msg":"總價/總面積","note":"","p":"","pimg":"bt_02.png","pu":"住家用","punit":"1","r":20,"reid":"","s":"43.30","sq":"5Dqv65D17Re6fnYQHmRWRkycldcdixsf7O6OqLYSzUQ=","t":"房地(土地+建物)","town":"P10","tp":"6,300,000","tunit":"1","type":"Sale","unit":"2","v":"3房2廳3衛"},{"AA11":"住","AA12":"","a":"林內鄉新興路","b":"透天厝","bn":"墅合院二","bs":"","bu":"F3棟0號","cinfo":"","city":"P","commid":"","cp":"","e":"111/06/22","es":"","f":"全/3","fi":"","g":"0","id":"48","j":"1","k":"1","l":"0","lat":23.76220315704935,"lon":120.61622983669216,"m":"","ma":"鋼筋混凝土造","msg":"總價/總面積","note":"","p":"","pimg":"bt_02.png","pu":"住家用","punit":"1","r":8,"reid":"","s":"42.14","sq":"l4u0Ul5WyO2fKk5z/my3rEycldcdixsf7O6OqLYSzUQ=","t":"房地(土地+建物)","town":"P10","tp":"7,500,000","tunit":"1","type":"Sale","unit":"2","v":"5房2廳3衛"},{"AA11":"住","AA12":"","a":"林內鄉新興路","b":"透天厝","bn":"墅合院","bs":"","bu":"D棟0號","cinfo":"","city":"P","commid":"","cp":"","e":"111/06/29","es":"","f":"全/3","fi":"","g":"0","id":"49","j":"1","k":"1","l":"0","lat":23.762329437680517,"lon":120.61618041269566,"m":"","ma":"鋼筋混凝土造","msg":"總價/總面積","note":"","p":"","pimg":"bt_02.png","pu":"住家用","punit":"1","r":9,"reid":"","s":"41.46","sq":"GdsMAd4zvX0vM4jOpg4LaUycldcdixsf7O6OqLYSzUQ=","t":"房地(土地+建物)","town":"P10","tp":"7,800,000","tunit":"1","type":"Sale","unit":"2","v":"5房2廳3衛"},{"AA11":"鄉村區","AA12":"乙種建築用地","a":"林內鄉民權路","b":"透天厝","bn":"姮興光禾墅","bs":"","bu":"B6棟0號","cinfo":"","city":"P","commid":"","cp":"","e":"111/05/29","es":"","f":"全/3","fi":"","g":"0","id":"50","j":"2","k":"1","l":"0","lat":23.747431461967555,"lon":120.6023140522801,"m":"","ma":"鋼筋混凝土造","msg":"總價/總面積","note":"","p":"","pimg":"bt_02.png","pu":"住家用","punit":"1","r":20,"reid":"","s":"44.00","sq":"Dge6qK3vi/LtgXCyNZr87Eycldcdixsf7O6OqLYSzUQ=","t":"房地(土地+建物)","town":"P10","tp":"6,550,000","tunit":"1","type":"Sale","unit":"2","v":"3房2廳3衛"},{"AA11":"鄉村區","AA12":"乙種建築用地","a":"林內鄉民權路","b":"透天厝","bn":"姮興光禾墅","bs":"","bu":"D2棟0號","cinfo":"","city":"P","commid":"","cp":"","e":"111/05/19","es":"","f":"全/3","fi":"","g":"0","id":"51","j":"2","k":"1","l":"0","lat":23.747367614740686,"lon":120.60206900602304,"m":"","ma":"鋼筋混凝土造","msg":"總價/總面積","note":"","p":"","pimg":"bt_02.png","pu":"住家用","punit":"1","r":20,"reid":"","s":"43.27","sq":"r3HnY1NQiTXhf5B5hOSCjEycldcdixsf7O6OqLYSzUQ=","t":"房地(土地+建物)","town":"P10","tp":"6,400,000","tunit":"1","type":"Sale","unit":"2","v":"3房2廳3衛"},{"AA11":"鄉村區","AA12":"乙種建築用地","a":"林內鄉民權路","b":"透天厝","bn":"姮興光禾墅","bs":"","bu":"D6棟0號","cinfo":"","city":"P","commid":"","cp":"","e":"111/05/07","es":"","f":"全/3","fi":"","g":"0","id":"52","j":"2","k":"1","l":"0","lat":23.747313720103406,"lon":120.60217707539522,"m":"","ma":"鋼筋混凝土造","msg":"總價/總面積","note":"","p":"","pimg":"bt_02.png","pu":"住家用","punit":"1","r":20,"reid":"","s":"43.27","sq":"cXHgDPg7agcFYh39IJ7Pu0ycldcdixsf7O6OqLYSzUQ=","t":"房地(土地+建物)","town":"P10","tp":"6,400,000","tunit":"1","type":"Sale","unit":"2","v":"3房2廳3衛"},{"AA11":"鄉村區","AA12":"乙種建築用地","a":"林內鄉民權路","b":"透天厝","bn":"姮興光禾墅","bs":"","bu":"D7棟0號","cinfo":"","city":"P","commid":"","cp":"","e":"111/04/03","es":"","f":"全/3","fi":"","g":"0","id":"53","j":"2","k":"1","l":"0","lat":23.74729576362253,"lon":120.60221636834082,"m":"","ma":"鋼筋混凝土造","msg":"總價/總面積","note":"","p":"","pimg":"bt_02.png","pu":"住家用","punit":"1","r":20,"reid":"","s":"43.30","sq":"SaJNqu+j2NA+wlLusJCWiEycldcdixsf7O6OqLYSzUQ=","t":"房地(土地+建物)","town":"P10","tp":"6,400,000","tunit":"1","type":"Sale","unit":"2","v":"3房2廳3衛"},{"AA11":"住","AA12":"","a":"林內鄉新興路","b":"透天厝","bn":"墅合院二","bs":"","bu":"F2棟0號","cinfo":"","city":"P","commid":"","cp":"","e":"111/04/19","es":"","f":"全/3","fi":"","g":"0","id":"54","j":"1","k":"1","l":"0","lat":23.762230340775933,"lon":120.61626899989993,"m":"","ma":"鋼筋混凝土造","msg":"總價/總面積","note":"","p":"","pimg":"bt_02.png","pu":"住家用","punit":"1","r":8,"reid":"","s":"42.14","sq":"nuuvGN6B1IPvpCZZCmls3kycldcdixsf7O6OqLYSzUQ=","t":"房地(土地+建物)","town":"P10","tp":"7,500,000","tunit":"1","type":"Sale","unit":"2","v":"5房2廳3衛"},{"AA11":"住","AA12":"","a":"林內鄉新興路","b":"透天厝","bn":"墅合院二","bs":"","bu":"F5棟0號","cinfo":"","city":"P","commid":"","cp":"","e":"111/04/17","es":"","f":"全/3","fi":"","g":"0","id":"55","j":"1","k":"1","l":"0","lat":23.762175997685908,"lon":120.61620048415553,"m":"","ma":"鋼筋混凝土造","msg":"總價/總面積","note":"","p":"","pimg":"bt_02.png","pu":"住家用","punit":"1","r":9,"reid":"","s":"42.14","sq":"BVv/v5SQvJH3WyBL1Z+AgUycldcdixsf7O6OqLYSzUQ=","t":"房地(土地+建物)","town":"P10","tp":"7,600,000","tunit":"1","type":"Sale","unit":"2","v":"5房2廳3衛"},{"AA11":"鄉村區","AA12":"乙種建築用地","a":"林內鄉民權路","b":"透天厝","bn":"姮興光禾墅","bs":"","bu":"D11棟0號","cinfo":"","city":"P","commid":"","cp":"","e":"111/03/13","es":"","f":"全/3","fi":"","g":"0","id":"56","j":"3","k":"1","l":"0","lat":23.747142563138166,"lon":120.60233454872468,"m":"","ma":"鋼筋混凝土造","msg":"總價/總面積","note":"","p":"","pimg":"bt_02.png","pu":"住家用","punit":"1","r":22,"reid":"","s":"51.41","sq":"znQKbDvonHnDjr8SpAJ/pUycldcdixsf7O6OqLYSzUQ=","t":"房地(土地+建物)","town":"P10","tp":"7,800,000","tunit":"1","type":"Sale","unit":"2","v":"4房2廳3衛"},{"AA11":"鄉村區","AA12":"乙種建築用地","a":"林內鄉民權路","b":"透天厝","bn":"姮興光禾墅","bs":"","bu":"D1棟0號","cinfo":"","city":"P","commid":"","cp":"","e":"111/03/15","es":"","f":"全/3","fi":"","g":"0","id":"57","j":"4","k":"1","l":"0","lat":23.747385611341695,"lon":120.60203952252074,"m":"","ma":"鋼筋混凝土造","msg":"總價/總面積","note":"","p":"","pimg":"bt_02.png","pu":"住家用","punit":"1","r":21,"reid":"","s":"43.06","sq":"xY2ks/U17Dxi1gwqQpSxukycldcdixsf7O6OqLYSzUQ=","t":"房地(土地+建物)","town":"P10","tp":"6,600,000","tunit":"1","type":"Sale","unit":"2","v":"3房2廳3衛"},{"AA11":"鄉村區","AA12":"乙種建築用地","a":"林內鄉民權路","b":"透天厝","bn":"姮興光禾墅","bs":"","bu":"B2棟0號","cinfo":"","city":"P","commid":"","cp":"","e":"111/03/07","es":"","f":"全/3","fi":"","g":"0","id":"58","j":"2","k":"1","l":"0","lat":23.747494385434486,"lon":120.60220595544052,"m":"","ma":"鋼筋混凝土造","msg":"總價/總面積","note":"","p":"","pimg":"bt_02.png","pu":"住家用","punit":"1","r":20,"reid":"","s":"43.97","sq":"ErqxYOl7DJD475LaRTzWxkycldcdixsf7O6OqLYSzUQ=","t":"房地(土地+建物)","town":"P10","tp":"6,450,000","tunit":"1","type":"Sale","unit":"2","v":"3房2廳3衛"},{"AA11":"鄉村區","AA12":"乙種建築用地","a":"林內鄉民權路","b":"透天厝","bn":"姮興光禾墅","bs":"","bu":"D8棟0號","cinfo":"","city":"P","commid":"","cp":"","e":"111/01/16","es":"","f":"全/3","fi":"","g":"0","id":"59","j":"3","k":"1","l":"0","lat":23.747178299434573,"lon":120.60218729634457,"m":"","ma":"鋼筋混凝土造","msg":"總價/總面積","note":"","p":"","pimg":"bt_02.png","pu":"住家用","punit":"1","r":23,"reid":"","s":"51.47","sq":"VcYRJopnEf6trTitE/P300ycldcdixsf7O6OqLYSzUQ=","t":"房地(土地+建物)","town":"P10","tp":"7,900,000","tunit":"1","type":"Sale","unit":"2","v":"4房2廳3衛"},{"AA11":"鄉村區","AA12":"乙種建築用地","a":"林內鄉民權路","b":"透天厝","bn":"姮興光禾墅","bs":"","bu":"E1棟0號","cinfo":"","city":"P","commid":"","cp":"","e":"111/01/02","es":"","f":"全/3","fi":"","g":"0","id":"60","j":"2","k":"1","l":"0","lat":23.74721514628791,"lon":120.60247166265033,"m":"","ma":"鋼筋混凝土造","msg":"總價/總面積","note":"1.林內鄉九芎段305地號等6筆土地於111年1月14日辦理合併、分割，分割後本案地號為305-35、305-18\n2.買受人名稱之姓氏誤植撤銷\n3.原申報書序號B1PA11101030003","p":"","pimg":"bt_02.png","pu":"住家用","punit":"1","r":21,"reid":"","s":"51.10","sq":"JoQtSbtMXWRlwLmhfc6S50ycldcdixsf7O6OqLYSzUQ=","t":"房地(土地+建物)","town":"P10","tp":"7,950,000","tunit":"1","type":"Sale","unit":"2","v":"3房2廳3衛"},{"AA11":"住","AA12":"","a":"林內鄉新興路","b":"透天厝","bn":"墅合院","bs":"","bu":"F1棟0號","cinfo":"","city":"P","commid":"","cp":"","e":"110/12/26","es":"","f":"全/3","fi":"","g":"0","id":"61","j":"1","k":"1","l":"0","lat":23.76227555762588,"lon":120.61629829952037,"m":"","ma":"鋼筋混凝土造","msg":"總價/總面積","note":"","p":"","pimg":"bt_02.png","pu":"住家用","punit":"1","r":10,"reid":"","s":"40.99","sq":"cSubYDetBZ/VodXI/Oo520ycldcdixsf7O6OqLYSzUQ=","t":"房地(土地+建物)","town":"P10","tp":"7,800,000","tunit":"1","type":"Sale","unit":"2","v":"5房2廳3衛"},{"AA11":"鄉村區","AA12":"乙種建築用地","a":"林內鄉民權路","b":"透天厝","bn":"姮興光禾墅","bs":"","bu":"D9棟0號","cinfo":"","city":"P","commid":"","cp":"","e":"110/12/25","es":"","f":"全/3","fi":"","g":"0","id":"62","j":"6","k":"1","l":"0","lat":23.747584813905167,"lon":120.60225472887676,"m":"","ma":"鋼筋混凝土造","msg":"總價/總面積","note":"1.本戶土地暫採未辦理合併分割前之權利範圍分配面積，後續產權登記仍以當地地政主管機關實際完成合併分割後之面積為準。2.本戶土地面積：含基地內通道持分土地面積、含迴車道土地面積。","p":"","pimg":"bt_02.png","pu":"住家用","punit":"1","r":11,"reid":"","s":"51.42","sq":"JGaPTZD6xfMqWCvlo348W0ycldcdixsf7O6OqLYSzUQ=","t":"房地(土地+建物)","town":"P10","tp":"6,900,000","tunit":"1","type":"Sale","unit":"2","v":"4房2廳3衛"},{"AA11":"鄉村區","AA12":"乙種建築用地","a":"林內鄉民權路","b":"透天厝","bn":"姮興光禾墅","bs":"","bu":"D10棟0號","cinfo":"","city":"P","commid":"","cp":"","e":"110/12/25","es":"","f":"全/3","fi":"","g":"0","id":"63","j":"6","k":"1","l":"0","lat":23.747584813905167,"lon":120.60225472887676,"m":"","ma":"鋼筋混凝土造","msg":"總價/總面積","note":"1.本戶土地暫採未辦理合併分割前之權利範圍分配面積，後續產權登記仍以當地地政主管機關實際完成合併分割後之面積為準。2.本戶土地面積：含基地內通道持分土地面積、含迴車道土地面積。","p":"","pimg":"bt_02.png","pu":"住家用","punit":"1","r":11,"reid":"","s":"51.41","sq":"w0NOOLLCeCPN7oYhqPPeVEycldcdixsf7O6OqLYSzUQ=","t":"房地(土地+建物)","town":"P10","tp":"6,900,000","tunit":"1","type":"Sale","unit":"2","v":"4房2廳3衛"},{"AA11":"住","AA12":"","a":"林內鄉新興路","b":"透天厝","bn":"墅合院","bs":"","bu":"F5棟0號","cinfo":"","city":"P","commid":"","cp":"","e":"110/11/11","es":"","f":"全/3","fi":"","g":"0","id":"64","j":"1","k":"1","l":"0","lat":23.762175997685908,"lon":120.61620048415553,"m":"","ma":"鋼筋混凝土造","msg":"總價/總面積","note":"","p":"","pimg":"bt_02.png","pu":"住家用","punit":"1","r":9,"reid":"","s":"40.51","sq":"p/xFh0r7UlYkMwbKzu5yLUycldcdixsf7O6OqLYSzUQ=","t":"房地(土地+建物)","town":"P10","tp":"7,580,000","tunit":"1","type":"Sale","unit":"2","v":"5房2廳3衛"},{"AA11":"鄉村區","AA12":"乙種建築用地","a":"林內鄉民權路","b":"透天厝","bn":"姮興光禾墅","bs":"","bu":"A2棟0號","cinfo":"","city":"P","commid":"","cp":"","e":"110/10/17","es":"","f":"全/3","fi":"","g":"0","id":"65","j":"6","k":"1","l":"0","lat":23.747584813905167,"lon":120.60225472887676,"m":"","ma":"鋼筋混凝土造","msg":"總價/總面積","note":"1.本戶土地暫採未辦理合併分割前之權利範圍分配面積，後續產權登記仍以當地地政主管機關實際完成合併分割後之面積為準。2.本戶土地面積：不含基地內通道持分土地面積及迴車道佔土地面積。","p":"","pimg":"bt_02.png","pu":"住家用","punit":"1","r":11,"reid":"","s":"43.69","sq":"QUnvl473GuLqpXytcJkq2Eycldcdixsf7O6OqLYSzUQ=","t":"房地(土地+建物)","town":"P10","tp":"6,400,000","tunit":"1","type":"Sale","unit":"2","v":"3房2廳3衛"},{"AA11":"鄉村區","AA12":"乙種建築用地","a":"林內鄉民權路","b":"透天厝","bn":"姮興光禾墅","bs":"","bu":"B9棟0號","cinfo":"","city":"P","commid":"","cp":"","e":"110/10/28","es":"","f":"全/3","fi":"","g":"0","id":"66","j":"6","k":"1","l":"0","lat":23.747584813905167,"lon":120.60225472887676,"m":"","ma":"鋼筋混凝土造","msg":"總價/總面積","note":"1.本戶土地暫採未辦理合併分割前之權利範圍分配面積，後續產權登記仍以當地地政主管機關實際完成合併分割後之面積為準。2.本戶土地面積：含基地內通道持分土地面積、不含迴車道佔土地面積。","p":"","pimg":"bt_02.png","pu":"住家用","punit":"1","r":11,"reid":"","s":"43.97","sq":"cw840TXsr1TXJOE6j+clL0ycldcdixsf7O6OqLYSzUQ=","t":"房地(土地+建物)","town":"P10","tp":"6,600,000","tunit":"1","type":"Sale","unit":"2","v":"3房2廳3衛"},{"AA11":"住","AA12":"","a":"林內鄉新興路","b":"透天厝","bn":"墅合院","bs":"","bu":"C棟0號","cinfo":"","city":"P","commid":"","cp":"","e":"110/10/13","es":"","f":"全/3","fi":"","g":"0","id":"67","j":"1","k":"1","l":"0","lat":23.762356465704908,"lon":120.61615090120839,"m":"","ma":"鋼骨鋼筋混凝土造","msg":"總價/總面積","note":"","p":"","pimg":"bt_02.png","pu":"住家用","punit":"1","r":9,"reid":"","s":"41.46","sq":"GbQaaIwmEJdKcH21cfHeokycldcdixsf7O6OqLYSzUQ=","t":"房地(土地+建物)","town":"P10","tp":"7,100,000","tunit":"1","type":"Sale","unit":"2","v":"5房2廳3衛"},{"AA11":"住","AA12":"","a":"林內鄉新興路","b":"透天厝","bn":"墅合院","bs":"","bu":"B棟0號","cinfo":"","city":"P","commid":"","cp":"","e":"110/10/19","es":"","f":"全/3","fi":"","g":"0","id":"68","j":"1","k":"1","l":"0","lat":23.76239250757209,"lon":120.61612136326892,"m":"","ma":"鋼筋混凝土造","msg":"總價/總面積","note":"","p":"","pimg":"bt_02.png","pu":"住家用","punit":"1","r":9,"reid":"","s":"41.46","sq":"B//h1UCPI1nX078Ija77GEycldcdixsf7O6OqLYSzUQ=","t":"房地(土地+建物)","town":"P10","tp":"7,300,000","tunit":"1","type":"Sale","unit":"2","v":"5房2廳3衛"},{"AA11":"住","AA12":"","a":"林內鄉新興路","b":"透天厝","bn":"墅合院","bs":"","bu":"A棟0號","cinfo":"","city":"P","commid":"","cp":"","e":"110/09/25","es":"","f":"全/3","fi":"","g":"0","id":"69","j":"1","k":"1","l":"0","lat":23.76241952068405,"lon":120.61609185179893,"m":"","ma":"鋼筋混凝土造","msg":"總價/總面積","note":"","p":"","pimg":"bt_02.png","pu":"住家用","punit":"1","r":10,"reid":"","s":"41.46","sq":"qNoYymsxcbWHhk+1pcNt1Eycldcdixsf7O6OqLYSzUQ=","t":"房地(土地+建物)","town":"P10","tp":"7,300,000","tunit":"1","type":"Sale","unit":"2","v":"5房2廳3衛"},{"AA11":"鄉村區","AA12":"乙種建築用地","a":"林內鄉民權路","b":"透天厝","bn":"姮興光禾墅","bs":"","bu":"B1棟0號","cinfo":"","city":"P","commid":"","cp":"","e":"110/09/19","es":"","f":"全/3","fi":"","g":"0","id":"70","j":"6","k":"1","l":"0","lat":23.747584813905167,"lon":120.60225472887676,"m":"","ma":"鋼筋混凝土造","msg":"總價/總面積","note":"1.本戶土地暫採未辦理合併分割前之權利範圍分配面積，後續產權登記仍以當地地政主管機關實際完成合併分割後之面積為準。2.本戶土地面積：含基地內通道持分土地面積、不含迴車道佔土地面積。","p":"","pimg":"bt_02.png","pu":"住家用","punit":"1","r":11,"reid":"","s":"46.65","sq":"O6vC1ZhKbP6UoIx/Pj+wIUycldcdixsf7O6OqLYSzUQ=","t":"房地(土地+建物)","town":"P10","tp":"6,600,000","tunit":"1","type":"Sale","unit":"2","v":"3房2廳3衛"},{"AA11":"鄉村區","AA12":"乙種建築用地","a":"林內鄉民權路","b":"透天厝","bn":"姮興光禾墅","bs":"","bu":"B7棟0號","cinfo":"","city":"P","commid":"","cp":"","e":"110/09/22","es":"","f":"全/3","fi":"","g":"0","id":"71","j":"6","k":"1","l":"0","lat":23.747584813905167,"lon":120.60225472887676,"m":"","ma":"鋼筋混凝土造","msg":"總價/總面積","note":"1.本戶土地暫採未辦理合併分割前之權利範圍分配面積，後續產權登記仍以當地地政主管機關實際完成合併分割後之面積為準。2.本戶土地面積：含基地內通道持分土地面積、不含迴車道佔土地面積。","p":"","pimg":"bt_02.png","pu":"住家用","punit":"1","r":11,"reid":"","s":"43.97","sq":"/C6I6lGHb+LyipKZ/aBoW0ycldcdixsf7O6OqLYSzUQ=","t":"房地(土地+建物)","town":"P10","tp":"6,350,000","tunit":"1","type":"Sale","unit":"2","v":"3房2廳3衛"},{"AA11":"鄉村區","AA12":"乙種建築用地","a":"林內鄉民權路","b":"透天厝","bn":"姮興光禾墅","bs":"","bu":"C1棟0號","cinfo":"","city":"P","commid":"","cp":"","e":"110/08/04","es":"","f":"全/3","fi":"","g":"0","id":"72","j":"6","k":"1","l":"0","lat":23.747584813905167,"lon":120.60225472887676,"m":"","ma":"鋼筋混凝土造","msg":"總價/總面積","note":"1.本戶土地暫採未辦理合併分割前之權利範圍分配面積，後續產權登記仍以當地地政主管機關實際完成合併分割後之面積為準。\n2.本戶土地面積：不含基地內通道持分土地面積及迴車道佔土地面積。","p":"","pimg":"bt_02.png","pu":"住家用","punit":"1","r":11,"reid":"","s":"43.79","sq":"5ntw4ToPxT9DL3CORHGGV0ycldcdixsf7O6OqLYSzUQ=","t":"房地(土地+建物)","town":"P10","tp":"7,000,000","tunit":"1","type":"Sale","unit":"2","v":"3房2廳3衛"},{"AA11":"鄉村區","AA12":"乙種建築用地","a":"林內鄉民權路","b":"透天厝","bn":"姮興光禾墅","bs":"","bu":"C2棟0號","cinfo":"","city":"P","commid":"","cp":"","e":"110/08/07","es":"","f":"全/3","fi":"","g":"0","id":"73","j":"6","k":"1","l":"0","lat":23.747584813905167,"lon":120.60225472887676,"m":"","ma":"鋼筋混凝土造","msg":"總價/總面積","note":"1.本戶土地暫採未辦理合併分割前之權利範圍分配面積，後續產權登記仍以當地地政主管機關實際完成合併分割後之面積為準。2.本戶土地面積：含基地內通道持分土地面積、不含迴車道佔土地面積。","p":"","pimg":"bt_02.png","pu":"住家用","punit":"1","r":11,"reid":"","s":"51.39","sq":"uZVEvElbMEBJ7KAGh4LaZ0ycldcdixsf7O6OqLYSzUQ=","t":"房地(土地+建物)","town":"P10","tp":"7,400,000","tunit":"1","type":"Sale","unit":"2","v":"3房2廳3衛"},{"AA11":"鄉村區","AA12":"乙種建築用地","a":"林內鄉民權路","b":"透天厝","bn":"姮興光禾墅","bs":"","bu":"B8棟0號","cinfo":"","city":"P","commid":"","cp":"","e":"110/08/23","es":"","f":"全/3","fi":"","g":"0","id":"74","j":"6","k":"1","l":"0","lat":23.747584813905167,"lon":120.60225472887676,"m":"","ma":"鋼筋混凝土造","msg":"總價/總面積","note":"1.本戶土地暫採未辦理合併分割前之權利範圍分配面積，後續產權登記仍以當地地政主管機關實際完成合併分割後之面積為準。2.本戶土地面積：含基地內通道持分土地面積、不含迴車道佔土地面積。","p":"","pimg":"bt_02.png","pu":"住家用","punit":"1","r":11,"reid":"","s":"44.00","sq":"A1R3il+AOF1IJ50xssx8gkycldcdixsf7O6OqLYSzUQ=","t":"房地(土地+建物)","town":"P10","tp":"6,350,000","tunit":"1","type":"Sale","unit":"2","v":"3房2廳3衛"},{"AA11":"住","AA12":"","a":"林內鄉新興路","b":"透天厝","bn":"墅合院","bs":"","bu":"E棟0號","cinfo":"","city":"P","commid":"","cp":"","e":"110/07/17","es":"","f":"全/3","fi":"","g":"0","id":"75","j":"1","k":"1","l":"0","lat":23.76228431830679,"lon":120.61619035575612,"m":"","ma":"鋼筋混凝土造","msg":"總價/總面積","note":"","p":"","pimg":"bt_02.png","pu":"住家用","punit":"1","r":11,"reid":"","s":"41.46","sq":"YoK+col4JCT7hPxhsY7bCUycldcdixsf7O6OqLYSzUQ=","t":"房地(土地+建物)","town":"P10","tp":"7,400,000","tunit":"1","type":"Sale","unit":"2","v":"5房2廳3衛"},{"AA11":"鄉村區","AA12":"乙種建築用地","a":"林內鄉民權路","b":"透天厝","bn":"姮興光禾墅","bs":"","bu":"A9棟0號","cinfo":"","city":"P","commid":"","cp":"","e":"110/07/14","es":"","f":"全/3","fi":"","g":"0","id":"76","j":"1","k":"1","l":"0","lat":23.747468157254342,"lon":120.60253956195332,"m":"","ma":"鋼筋混凝土造","msg":"總價/總面積","note":"1.305地號等6筆土地於111年1月14日合併、分割，本案基地號305-7\n2.本戶土地面積不含基地內通道持分土地面積及迴車道佔土地面積\n3.總價誤植撤銷；原申報書序號B1PA11007260006","p":"","pimg":"bt_02.png","pu":"住家用","punit":"1","r":12,"reid":"","s":"53.85","sq":"QTIqFBTBvi88njK2lATnXUycldcdixsf7O6OqLYSzUQ=","t":"房地(土地+建物)","town":"P10","tp":"7,200,000","tunit":"1","type":"Sale","unit":"2","v":"3房2廳3衛"},{"AA11":"鄉村區","AA12":"乙種建築用地","a":"林內鄉民權路","b":"透天厝","bn":"姮興光禾墅","bs":"","bu":"A1棟0號","cinfo":"","city":"P","commid":"","cp":"","e":"110/07/16","es":"","f":"全/3","fi":"","g":"0","id":"77","j":"6","k":"1","l":"0","lat":23.747584813905167,"lon":120.60225472887676,"m":"","ma":"鋼筋混凝土造","msg":"總價/總面積","note":"1.本戶土地暫採未辦理合併分割前之權利範圍分配面積，後續產權登記仍以當地地政主管機關實際完成合併分割後之面積為準。\n2.本戶土地面積不含基地內通道持分土地面積及迴車道佔土地面積。","p":"","pimg":"bt_02.png","pu":"住家用","punit":"1","r":11,"reid":"","s":"53.21","sq":"LBb7cPYN/iLI8n1/zwYT2Uycldcdixsf7O6OqLYSzUQ=","t":"房地(土地+建物)","town":"P10","tp":"7,000,000","tunit":"1","type":"Sale","unit":"2","v":"3房2廳3衛"}]